amqp_events/__init__.py
amqp_events/celery.py
amqp_events/config.py
amqp_events/defaults.py
amqp_events/task.py
amqp_events/types.py
celery_amqp_events-0.1.0.dist-info/LICENSE
celery_amqp_events-0.1.0.dist-info/METADATA
celery_amqp_events-0.1.0.dist-info/WHEEL
celery_amqp_events-0.1.0.dist-info/top_level.txt
celery_amqp_events-0.1.0.dist-info/RECORD
