Metadata-Version: 2.1
Name: celery-amqp-events
Version: 0.1.0
Summary: Distributed event handling on top of Celery
Home-page: https://github.com/just-work/celery-amqp-events
Author: Sergey Tikhonov
Author-email: zimbler@gmail.com
License: MIT
Platform: UNKNOWN
Classifier: Development Status :: 4 - Beta
Classifier: Environment :: Console
Classifier: Operating System :: POSIX
Classifier: Programming Language :: Python :: 3.7
Classifier: Programming Language :: Python :: 3.8
Classifier: Programming Language :: Python :: 3.9
Classifier: Programming Language :: Python :: 3.10
Classifier: Topic :: Software Development :: Libraries
Classifier: Topic :: System :: Distributed Computing
License-File: LICENSE
Requires-Dist: Celery
Requires-Dist: typing-extensions ; python_version < "3.8.0"
